webplucker/__init__.py
webplucker/jsengine/__init__.py
webplucker/req_handler/__init__.py
webplucker/req_handler/agents/__init__.py
webplucker/req_handler/extractdata/__init__.py
webplucker/req_handler/extractdata/config.py
webplucker-0.0.8.dist-info/LICENSE
webplucker-0.0.8.dist-info/METADATA
webplucker-0.0.8.dist-info/WHEEL
webplucker-0.0.8.dist-info/top_level.txt
webplucker-0.0.8.dist-info/RECORD
